dripconfig/__init__.py
dripconfig/builtins.py
dripconfig/configdict.py
dripconfig/helpers.py
dripconfig/interfaces.py
dripconfig/sources.py
dripconfig-0.2.5.dist-info/DESCRIPTION.rst
dripconfig-0.2.5.dist-info/METADATA
dripconfig-0.2.5.dist-info/RECORD
dripconfig-0.2.5.dist-info/WHEEL
dripconfig-0.2.5.dist-info/metadata.json
dripconfig-0.2.5.dist-info/top_level.txt
tests/__init__.py
tests/dripconfig/__init__.py
tests/dripconfig/test_configdict.py
tests/dripconfig/test_helpers.py
tests/dripconfig/test_injection.py
