Metadata-Version: 2.0
Name: dripconfig
Version: 0.2.5
Summary: configuration loading utilities for common process setup tasks
Home-page: UNKNOWN
Author: Luke Tucker, James O'Beirne
Author-email: luke@percolate.com, jamesob@percolate.com
License: UNKNOWN
Platform: UNKNOWN
Requires-Dist: configparser (>=3.3.0)
Requires-Dist: jsmin (>=2.0.6)
Requires-Dist: pyyaml
Requires-Dist: voluptuous (>=0.8.3)
Provides-Extra: builtins
Requires-Dist: python-statsd (>=1.6.0); extra == 'builtins'
Requires-Dist: raven (==1.9.1); extra == 'builtins'
